byted_kvcache_agent/__init__.py
byted_kvcache_agent-0.0.1.dist-info/METADATA
byted_kvcache_agent-0.0.1.dist-info/WHEEL
byted_kvcache_agent-0.0.1.dist-info/top_level.txt
byted_kvcache_agent-0.0.1.dist-info/RECORD
