Metadata-Version: 2.1
Name: byted-kvcache-agent
Version: 0.0.1
Summary: A simple package named byted_kvcache_agent
Home-page: https://github.com/artifact/byted_kvcache_agent.git
Author: artifact
Author-email: artifact@example.com
License: UNKNOWN
Platform: UNKNOWN
Classifier: Programming Language :: Python :: 3
Classifier: License :: OSI Approved :: MIT License
Classifier: Operating System :: OS Independent
